nauts_ml_envs/__init__.py
nauts_ml_envs/space_evaders/__init__.py
nauts_ml_envs/space_evaders/space_evaders.py
nauts_ml_envs-2.2.0.dist-info/LICENSE
nauts_ml_envs-2.2.0.dist-info/METADATA
nauts_ml_envs-2.2.0.dist-info/WHEEL
nauts_ml_envs-2.2.0.dist-info/top_level.txt
nauts_ml_envs-2.2.0.dist-info/RECORD
