Metadata-Version: 2.1
Name: nauts-ml-envs
Version: 2.2.0
Summary: Python library of environments to facilitate practicing machine learning
Home-page: https://github.com/mathstronauts/mathstropy
Author: Richard Hamilton
Author-email: r.hamilton@mathstronauts.ca
License: UNKNOWN
Platform: UNKNOWN
Classifier: Programming Language :: Python :: 3
Classifier: License :: OSI Approved :: MIT License
Classifier: Operating System :: OS Independent
Requires-Python: >=3.6
License-File: LICENSE
Requires-Dist: pygame
Requires-Dist: matplotlib
Requires-Dist: mathstropy
